tessng2other/__init__.py
tessng2other/opendrive/__init__.py
tessng2other/opendrive/config.py
tessng2other/opendrive/functions.py
tessng2other/opendrive/models.py
tessng2other/opendrive/node.py
tessng2other/unity/__init__.py
tessng2other/unity/config.py
tessng2other/unity/functions.py
tessng2other/unity/unity_utils.py
tessng2other-0.0.1.dist-info/LICENSE
tessng2other-0.0.1.dist-info/METADATA
tessng2other-0.0.1.dist-info/WHEEL
tessng2other-0.0.1.dist-info/top_level.txt
tessng2other-0.0.1.dist-info/RECORD
