Metadata-Version: 2.1
Name: tessng2other
Version: 0.0.1
Summary: convert tessng to file
Home-page: UNKNOWN
Author: Author
Author-email: 17315487709@163.com
License: UNKNOWN
Platform: UNKNOWN
Classifier: Programming Language :: Python :: 3
Classifier: License :: OSI Approved :: MIT License
Classifier: Operating System :: OS Independent
Requires-Python: >=3.6, <=3.9
License-File: LICENSE
